funkload_friendly/__init__.py
funkload_friendly/cookie.py
funkload_friendly/datatypes.py
funkload_friendly/test.py
funkload_friendly-0.2.dist-info/DESCRIPTION.rst
funkload_friendly-0.2.dist-info/METADATA
funkload_friendly-0.2.dist-info/RECORD
funkload_friendly-0.2.dist-info/WHEEL
funkload_friendly-0.2.dist-info/metadata.json
funkload_friendly-0.2.dist-info/top_level.txt
