Metadata-Version: 2.0
Name: funkload-friendly
Version: 0.2
Summary: Friendly wrapper of Funkload.
Home-page: https://github.com/tokibito/funkload-friendly
Author: Shinya Okano
Author-email: tokibito@gmail.com
License: UNKNOWN
Platform: UNKNOWN
Classifier: Development Status :: 3 - Alpha
Classifier: Programming Language :: Python :: 2.7
Classifier: License :: OSI Approved :: MIT License
Requires-Dist: funkload (>=1.17.1)
